[
  {
    "id": "job-f856c4636112729e5471174e",
    "config": {
      "From": "noreply@acme.example",
      "FromName": "Acme Product Team",
      "EnvelopeFrom": "noreply@acme.example",
      "ReturnPath": "",
      "ReplyTo": null,
      "To": [
        "demo@example.org"
      ],
      "CC": null,
      "BCC": null,
      "ListUnsubscribe": null,
      "ListUnsubscribePost": false,
      "Subject": "Welcome to Acme — Start here",
      "Body": "",
      "TextBody": "Welcome to Acme!\n\nHello demo@example.org,\n\nThank you for joining Acme on 2025-12-20T22:15:03+05:45 — this email is part of the \"(none)\" step in your onboarding workflow.\n\nQuick links:\n  - Log in: https://app.example/login\n  - Quickstart tour: https://app.example/tour\n\n— The Acme Product Team",
      "HTMLBody": "\u003c!doctype html\u003e\n\u003chtml\u003e\n\u003chead\u003e\n  \u003cmeta charset=\"utf-8\"\u003e\n  \u003ctitle\u003eWelcome to Acme\u003c/title\u003e\n\u003c/head\u003e\n\u003cbody\u003e\n  \u003ch1\u003eWelcome to Acme!\u003c/h1\u003e\n  \u003cp\u003eHello demo@example.org,\u003c/p\u003e\n  \u003cp\u003eThank you for joining Acme on 2025-12-20T22:15:03+05:45 — this email is part of the \u003cstrong\u003e(none)\u003c/strong\u003e step in your onboarding workflow.\u003c/p\u003e\n  \u003cp\u003eQuick links:\n    \u003cul\u003e\n      \u003cli\u003e\u003ca href=\"https://app.example/login\"\u003eLog in\u003c/a\u003e\u003c/li\u003e\n      \u003cli\u003e\u003ca href=\"https://app.example/tour\"\u003eTry the quickstart tour\u003c/a\u003e\u003c/li\u003e\n    \u003c/ul\u003e\n  \u003c/p\u003e\n  \u003cp\u003e— The Acme Product Team\u003c/p\u003e\n\u003c/body\u003e\n\u003c/html\u003e",
      "Attachments": null,
      "ConfigurationSet": "",
      "Tags": {},
      "Provider": "[smtp]",
      "Transport": "smtp",
      "Host": "localhost",
      "Port": 1025,
      "Username": "noreply@acme.example",
      "Password": "",
      "APIKey": "",
      "APIToken": "",
      "Endpoint": "",
      "HTTPMethod": "POST",
      "Headers": {},
      "QueryParams": {},
      "HTTPPayload": null,
      "PayloadFormat": "",
      "HTTPContentType": "",
      "HTTPAuth": "",
      "HTTPAuthHeader": "",
      "HTTPAuthQuery": "",
      "HTTPAuthPrefix": "Bearer",
      "MaxConnsPerHost": 0,
      "MaxIdleConns": 0,
      "MaxIdleConnsHost": 0,
      "DisableKeepAlives": false,
      "SMTPAuth": "",
      "HTMLTemplatePath": "templates/pipeline_welcome_mailhog.html",
      "TextTemplatePath": "templates/pipeline_welcome_mailhog.txt",
      "BodyTemplatePath": "",
      "AdditionalData": {
        "login_url": "https://app.example/login",
        "step": "(none)",
        "tour_url": "https://app.example/tour",
        "workflow_steps": [
          {
            "delay_seconds": 0,
            "name": "welcome",
            "provider_priority": [
              "smtp"
            ],
            "retry_count": 2,
            "retry_delay_seconds": 5,
            "subject": "Welcome to Acme — Start here"
          },
          {
            "body": "Hi demo@example.org, just checking in to see how things are going. Login: https://app.example/login",
            "delay_seconds": 60,
            "name": "followup",
            "provider_priority": [
              "smtp"
            ],
            "retry_count": 2,
            "subject": "A quick follow-up"
          }
        ]
      },
      "AWSRegion": "",
      "AWSAccessKey": "",
      "AWSSecretKey": "",
      "AWSSessionToken": "",
      "UseTLS": false,
      "UseSSL": false,
      "SkipTLSVerify": false,
      "Timeout": 15000000000,
      "RetryCount": 2,
      "RetryDelay": 5000000000,
      "MaxRetryDelay": 0,
      "ProviderPriority": [
        "smtp"
      ]
    },
    "run_at": "2025-12-20T16:30:03.821328003Z",
    "attempts": 0,
    "meta": {
      "name": "welcome",
      "step": "welcome",
      "step_index": 0
    }
  },
  {
    "id": "job-0c9272aa0cbcd957f3caa311",
    "config": {
      "From": "noreply@acme.example",
      "FromName": "Acme Product Team",
      "EnvelopeFrom": "noreply@acme.example",
      "ReturnPath": "",
      "ReplyTo": null,
      "To": [
        "demo@example.org"
      ],
      "CC": null,
      "BCC": null,
      "ListUnsubscribe": null,
      "ListUnsubscribePost": false,
      "Subject": "A quick follow-up",
      "Body": "Hi demo@example.org, just checking in to see how things are going. Login: https://app.example/login",
      "TextBody": "Hi demo@example.org, just checking in to see how things are going. Login: https://app.example/login",
      "HTMLBody": "\u003c!doctype html\u003e\n\u003chtml\u003e\n\u003chead\u003e\n  \u003cmeta charset=\"utf-8\"\u003e\n  \u003ctitle\u003eWelcome to Acme\u003c/title\u003e\n\u003c/head\u003e\n\u003cbody\u003e\n  \u003ch1\u003eWelcome to Acme!\u003c/h1\u003e\n  \u003cp\u003eHello demo@example.org,\u003c/p\u003e\n  \u003cp\u003eThank you for joining Acme on 2025-12-20T22:15:03+05:45 — this email is part of the \u003cstrong\u003e(none)\u003c/strong\u003e step in your onboarding workflow.\u003c/p\u003e\n  \u003cp\u003eQuick links:\n    \u003cul\u003e\n      \u003cli\u003e\u003ca href=\"https://app.example/login\"\u003eLog in\u003c/a\u003e\u003c/li\u003e\n      \u003cli\u003e\u003ca href=\"https://app.example/tour\"\u003eTry the quickstart tour\u003c/a\u003e\u003c/li\u003e\n    \u003c/ul\u003e\n  \u003c/p\u003e\n  \u003cp\u003e— The Acme Product Team\u003c/p\u003e\n\u003c/body\u003e\n\u003c/html\u003e",
      "Attachments": null,
      "ConfigurationSet": "",
      "Tags": {},
      "Provider": "[smtp]",
      "Transport": "smtp",
      "Host": "localhost",
      "Port": 1025,
      "Username": "noreply@acme.example",
      "Password": "",
      "APIKey": "",
      "APIToken": "",
      "Endpoint": "",
      "HTTPMethod": "POST",
      "Headers": {},
      "QueryParams": {},
      "HTTPPayload": null,
      "PayloadFormat": "",
      "HTTPContentType": "",
      "HTTPAuth": "",
      "HTTPAuthHeader": "",
      "HTTPAuthQuery": "",
      "HTTPAuthPrefix": "Bearer",
      "MaxConnsPerHost": 0,
      "MaxIdleConns": 0,
      "MaxIdleConnsHost": 0,
      "DisableKeepAlives": false,
      "SMTPAuth": "",
      "HTMLTemplatePath": "templates/pipeline_welcome_mailhog.html",
      "TextTemplatePath": "templates/pipeline_welcome_mailhog.txt",
      "BodyTemplatePath": "",
      "AdditionalData": {
        "login_url": "https://app.example/login",
        "step": "(none)",
        "tour_url": "https://app.example/tour",
        "workflow_steps": [
          {
            "delay_seconds": 0,
            "name": "welcome",
            "provider_priority": [
              "smtp"
            ],
            "retry_count": 2,
            "retry_delay_seconds": 5,
            "subject": "Welcome to Acme — Start here"
          },
          {
            "body": "Hi demo@example.org, just checking in to see how things are going. Login: https://app.example/login",
            "delay_seconds": 60,
            "name": "followup",
            "provider_priority": [
              "smtp"
            ],
            "retry_count": 2,
            "subject": "A quick follow-up"
          }
        ]
      },
      "AWSRegion": "",
      "AWSAccessKey": "",
      "AWSSecretKey": "",
      "AWSSessionToken": "",
      "UseTLS": false,
      "UseSSL": false,
      "SkipTLSVerify": false,
      "Timeout": 15000000000,
      "RetryCount": 2,
      "RetryDelay": 5000000000,
      "MaxRetryDelay": 0,
      "ProviderPriority": [
        "smtp"
      ]
    },
    "run_at": "2025-12-20T16:31:03.821328003Z",
    "attempts": 0,
    "meta": {
      "name": "followup",
      "step": "followup",
      "step_index": 1
    }
  },
  {
    "id": "job-acb9c6c7e934041625fab48f",
    "config": {
      "From": "noreply@acme.example",
      "FromName": "Acme Product Team",
      "EnvelopeFrom": "noreply@acme.example",
      "ReturnPath": "",
      "ReplyTo": null,
      "To": [
        "demo@example.org"
      ],
      "CC": null,
      "BCC": null,
      "ListUnsubscribe": null,
      "ListUnsubscribePost": false,
      "Subject": "Welcome to Acme — Start here",
      "Body": "",
      "TextBody": "Welcome to Acme!\n\nHello demo@example.org,\n\nThank you for joining Acme on 2025-12-20T22:19:15+05:45 — this email is part of the \"\" step in your onboarding workflow.\n\nQuick links:\n  - Log in: https://app.example/login\n  - Quickstart tour: https://app.example/tour\n\n— The Acme Product Team",
      "HTMLBody": "\u003c!doctype html\u003e\n\u003chtml\u003e\n\u003chead\u003e\n  \u003cmeta charset=\"utf-8\"\u003e\n  \u003ctitle\u003eWelcome to Acme\u003c/title\u003e\n\u003c/head\u003e\n\u003cbody\u003e\n  \u003ch1\u003eWelcome to Acme!\u003c/h1\u003e\n  \u003cp\u003eHello demo@example.org,\u003c/p\u003e\n  \u003cp\u003eThank you for joining Acme on 2025-12-20T22:19:15+05:45 — this email is part of the \u003cstrong\u003e\u003c/strong\u003e step in your onboarding workflow.\u003c/p\u003e\n  \u003cp\u003eQuick links:\n    \u003cul\u003e\n      \u003cli\u003e\u003ca href=\"https://app.example/login\"\u003eLog in\u003c/a\u003e\u003c/li\u003e\n      \u003cli\u003e\u003ca href=\"https://app.example/tour\"\u003eTry the quickstart tour\u003c/a\u003e\u003c/li\u003e\n    \u003c/ul\u003e\n  \u003c/p\u003e\n  \u003cp\u003e— The Acme Product Team\u003c/p\u003e\n\u003c/body\u003e\n\u003c/html\u003e",
      "Attachments": null,
      "ConfigurationSet": "",
      "Tags": {},
      "Provider": "[smtp]",
      "Transport": "smtp",
      "Host": "localhost",
      "Port": 1025,
      "Username": "noreply@acme.example",
      "Password": "",
      "APIKey": "",
      "APIToken": "",
      "Endpoint": "",
      "HTTPMethod": "POST",
      "Headers": {},
      "QueryParams": {},
      "HTTPPayload": null,
      "PayloadFormat": "",
      "HTTPContentType": "",
      "HTTPAuth": "",
      "HTTPAuthHeader": "",
      "HTTPAuthQuery": "",
      "HTTPAuthPrefix": "Bearer",
      "MaxConnsPerHost": 0,
      "MaxIdleConns": 0,
      "MaxIdleConnsHost": 0,
      "DisableKeepAlives": false,
      "SMTPAuth": "",
      "HTMLTemplatePath": "templates/pipeline_welcome_mailhog.html",
      "TextTemplatePath": "templates/pipeline_welcome_mailhog.txt",
      "BodyTemplatePath": "",
      "AdditionalData": {
        "login_url": "https://app.example/login",
        "tour_url": "https://app.example/tour",
        "workflow_steps": [
          {
            "delay_seconds": 0,
            "name": "welcome",
            "provider_priority": [
              "smtp"
            ],
            "retry_count": 2,
            "retry_delay_seconds": 5,
            "subject": "Welcome to Acme — Start here"
          },
          {
            "body": "Hi demo@example.org, just checking in to see how things are going. Login: https://app.example/login",
            "delay_seconds": 60,
            "name": "followup",
            "provider_priority": [
              "smtp"
            ],
            "retry_count": 2,
            "subject": "A quick follow-up"
          }
        ]
      },
      "AWSRegion": "",
      "AWSAccessKey": "",
      "AWSSecretKey": "",
      "AWSSessionToken": "",
      "UseTLS": false,
      "UseSSL": false,
      "SkipTLSVerify": false,
      "Timeout": 15000000000,
      "RetryCount": 2,
      "RetryDelay": 5000000000,
      "MaxRetryDelay": 0,
      "ProviderPriority": [
        "smtp"
      ]
    },
    "run_at": "2025-12-20T16:34:15.347511268Z",
    "attempts": 0,
    "meta": {
      "name": "welcome",
      "step": "welcome",
      "step_index": 0
    }
  },
  {
    "id": "job-b3c9b3e46ab87aadb83bc9f3",
    "config": {
      "From": "noreply@acme.example",
      "FromName": "Acme Product Team",
      "EnvelopeFrom": "noreply@acme.example",
      "ReturnPath": "",
      "ReplyTo": null,
      "To": [
        "demo@example.org"
      ],
      "CC": null,
      "BCC": null,
      "ListUnsubscribe": null,
      "ListUnsubscribePost": false,
      "Subject": "Welcome to Acme — Start here",
      "Body": "",
      "TextBody": "Welcome to Acme!\n\nHello demo@example.org,\n\nThank you for joining Acme on 2025-12-20T22:20:09+05:45 — this email is part of the \"\" step in your onboarding workflow.\n\nQuick links:\n  - Log in: https://app.example/login\n  - Quickstart tour: https://app.example/tour\n\n— The Acme Product Team",
      "HTMLBody": "\u003c!doctype html\u003e\n\u003chtml\u003e\n\u003chead\u003e\n  \u003cmeta charset=\"utf-8\"\u003e\n  \u003ctitle\u003eWelcome to Acme\u003c/title\u003e\n\u003c/head\u003e\n\u003cbody\u003e\n  \u003ch1\u003eWelcome to Acme!\u003c/h1\u003e\n  \u003cp\u003eHello demo@example.org,\u003c/p\u003e\n  \u003cp\u003eThank you for joining Acme on 2025-12-20T22:20:09+05:45 — this email is part of the \u003cstrong\u003e\u003c/strong\u003e step in your onboarding workflow.\u003c/p\u003e\n  \u003cp\u003eQuick links:\n    \u003cul\u003e\n      \u003cli\u003e\u003ca href=\"https://app.example/login\"\u003eLog in\u003c/a\u003e\u003c/li\u003e\n      \u003cli\u003e\u003ca href=\"https://app.example/tour\"\u003eTry the quickstart tour\u003c/a\u003e\u003c/li\u003e\n    \u003c/ul\u003e\n  \u003c/p\u003e\n  \u003cp\u003e— The Acme Product Team\u003c/p\u003e\n\u003c/body\u003e\n\u003c/html\u003e",
      "Attachments": null,
      "ConfigurationSet": "",
      "Tags": {},
      "Provider": "[smtp]",
      "Transport": "smtp",
      "Host": "localhost",
      "Port": 1025,
      "Username": "noreply@acme.example",
      "Password": "",
      "APIKey": "",
      "APIToken": "",
      "Endpoint": "",
      "HTTPMethod": "POST",
      "Headers": {},
      "QueryParams": {},
      "HTTPPayload": null,
      "PayloadFormat": "",
      "HTTPContentType": "",
      "HTTPAuth": "",
      "HTTPAuthHeader": "",
      "HTTPAuthQuery": "",
      "HTTPAuthPrefix": "Bearer",
      "MaxConnsPerHost": 0,
      "MaxIdleConns": 0,
      "MaxIdleConnsHost": 0,
      "DisableKeepAlives": false,
      "SMTPAuth": "",
      "HTMLTemplatePath": "templates/pipeline_welcome_mailhog.html",
      "TextTemplatePath": "templates/pipeline_welcome_mailhog.txt",
      "BodyTemplatePath": "",
      "AdditionalData": {
        "login_url": "https://app.example/login",
        "tour_url": "https://app.example/tour",
        "workflow_steps": [
          {
            "delay_seconds": 0,
            "name": "welcome",
            "provider_priority": [
              "smtp"
            ],
            "retry_count": 2,
            "retry_delay_seconds": 5,
            "subject": "Welcome to Acme — Start here"
          },
          {
            "body": "Hi demo@example.org, just checking in to see how things are going. Login: https://app.example/login",
            "delay_seconds": 60,
            "name": "followup",
            "provider_priority": [
              "smtp"
            ],
            "retry_count": 2,
            "subject": "A quick follow-up"
          }
        ]
      },
      "AWSRegion": "",
      "AWSAccessKey": "",
      "AWSSecretKey": "",
      "AWSSessionToken": "",
      "UseTLS": false,
      "UseSSL": false,
      "SkipTLSVerify": false,
      "Timeout": 15000000000,
      "RetryCount": 2,
      "RetryDelay": 5000000000,
      "MaxRetryDelay": 0,
      "ProviderPriority": [
        "smtp"
      ]
    },
    "run_at": "2025-12-20T16:35:09.872917332Z",
    "attempts": 0,
    "meta": {
      "name": "welcome",
      "step": "welcome",
      "step_index": 0
    }
  },
  {
    "id": "job-5cf56888333f8cee1a74026c",
    "config": {
      "From": "noreply@acme.example",
      "FromName": "Acme Product Team",
      "EnvelopeFrom": "noreply@acme.example",
      "ReturnPath": "",
      "ReplyTo": null,
      "To": [
        "demo@example.org"
      ],
      "CC": null,
      "BCC": null,
      "ListUnsubscribe": null,
      "ListUnsubscribePost": false,
      "Subject": "A quick follow-up",
      "Body": "Hi demo@example.org, just checking in to see how things are going. Login: https://app.example/login",
      "TextBody": "Hi demo@example.org, just checking in to see how things are going. Login: https://app.example/login",
      "HTMLBody": "\u003c!doctype html\u003e\n\u003chtml\u003e\n\u003chead\u003e\n  \u003cmeta charset=\"utf-8\"\u003e\n  \u003ctitle\u003eWelcome to Acme\u003c/title\u003e\n\u003c/head\u003e\n\u003cbody\u003e\n  \u003ch1\u003eWelcome to Acme!\u003c/h1\u003e\n  \u003cp\u003eHello demo@example.org,\u003c/p\u003e\n  \u003cp\u003eThank you for joining Acme on 2025-12-20T22:19:15+05:45 — this email is part of the \u003cstrong\u003e\u003c/strong\u003e step in your onboarding workflow.\u003c/p\u003e\n  \u003cp\u003eQuick links:\n    \u003cul\u003e\n      \u003cli\u003e\u003ca href=\"https://app.example/login\"\u003eLog in\u003c/a\u003e\u003c/li\u003e\n      \u003cli\u003e\u003ca href=\"https://app.example/tour\"\u003eTry the quickstart tour\u003c/a\u003e\u003c/li\u003e\n    \u003c/ul\u003e\n  \u003c/p\u003e\n  \u003cp\u003e— The Acme Product Team\u003c/p\u003e\n\u003c/body\u003e\n\u003c/html\u003e",
      "Attachments": null,
      "ConfigurationSet": "",
      "Tags": {},
      "Provider": "[smtp]",
      "Transport": "smtp",
      "Host": "localhost",
      "Port": 1025,
      "Username": "noreply@acme.example",
      "Password": "",
      "APIKey": "",
      "APIToken": "",
      "Endpoint": "",
      "HTTPMethod": "POST",
      "Headers": {},
      "QueryParams": {},
      "HTTPPayload": null,
      "PayloadFormat": "",
      "HTTPContentType": "",
      "HTTPAuth": "",
      "HTTPAuthHeader": "",
      "HTTPAuthQuery": "",
      "HTTPAuthPrefix": "Bearer",
      "MaxConnsPerHost": 0,
      "MaxIdleConns": 0,
      "MaxIdleConnsHost": 0,
      "DisableKeepAlives": false,
      "SMTPAuth": "",
      "HTMLTemplatePath": "templates/pipeline_welcome_mailhog.html",
      "TextTemplatePath": "templates/pipeline_welcome_mailhog.txt",
      "BodyTemplatePath": "",
      "AdditionalData": {
        "login_url": "https://app.example/login",
        "tour_url": "https://app.example/tour",
        "workflow_steps": [
          {
            "delay_seconds": 0,
            "name": "welcome",
            "provider_priority": [
              "smtp"
            ],
            "retry_count": 2,
            "retry_delay_seconds": 5,
            "subject": "Welcome to Acme — Start here"
          },
          {
            "body": "Hi demo@example.org, just checking in to see how things are going. Login: https://app.example/login",
            "delay_seconds": 60,
            "name": "followup",
            "provider_priority": [
              "smtp"
            ],
            "retry_count": 2,
            "subject": "A quick follow-up"
          }
        ]
      },
      "AWSRegion": "",
      "AWSAccessKey": "",
      "AWSSecretKey": "",
      "AWSSessionToken": "",
      "UseTLS": false,
      "UseSSL": false,
      "SkipTLSVerify": false,
      "Timeout": 15000000000,
      "RetryCount": 2,
      "RetryDelay": 5000000000,
      "MaxRetryDelay": 0,
      "ProviderPriority": [
        "smtp"
      ]
    },
    "run_at": "2025-12-20T16:35:15.347511268Z",
    "attempts": 0,
    "meta": {
      "name": "followup",
      "step": "followup",
      "step_index": 1
    }
  },
  {
    "id": "job-ae0ebcd437375bda306eac6f",
    "config": {
      "From": "noreply@acme.example",
      "FromName": "Acme Product Team",
      "EnvelopeFrom": "noreply@acme.example",
      "ReturnPath": "",
      "ReplyTo": null,
      "To": [
        "demo@example.org"
      ],
      "CC": null,
      "BCC": null,
      "ListUnsubscribe": null,
      "ListUnsubscribePost": false,
      "Subject": "A quick follow-up",
      "Body": "Hi demo@example.org, just checking in to see how things are going. Login: https://app.example/login",
      "TextBody": "Hi demo@example.org, just checking in to see how things are going. Login: https://app.example/login",
      "HTMLBody": "\u003c!doctype html\u003e\n\u003chtml\u003e\n\u003chead\u003e\n  \u003cmeta charset=\"utf-8\"\u003e\n  \u003ctitle\u003eWelcome to Acme\u003c/title\u003e\n\u003c/head\u003e\n\u003cbody\u003e\n  \u003ch1\u003eWelcome to Acme!\u003c/h1\u003e\n  \u003cp\u003eHello demo@example.org,\u003c/p\u003e\n  \u003cp\u003eThank you for joining Acme on 2025-12-20T22:20:09+05:45 — this email is part of the \u003cstrong\u003e\u003c/strong\u003e step in your onboarding workflow.\u003c/p\u003e\n  \u003cp\u003eQuick links:\n    \u003cul\u003e\n      \u003cli\u003e\u003ca href=\"https://app.example/login\"\u003eLog in\u003c/a\u003e\u003c/li\u003e\n      \u003cli\u003e\u003ca href=\"https://app.example/tour\"\u003eTry the quickstart tour\u003c/a\u003e\u003c/li\u003e\n    \u003c/ul\u003e\n  \u003c/p\u003e\n  \u003cp\u003e— The Acme Product Team\u003c/p\u003e\n\u003c/body\u003e\n\u003c/html\u003e",
      "Attachments": null,
      "ConfigurationSet": "",
      "Tags": {},
      "Provider": "[smtp]",
      "Transport": "smtp",
      "Host": "localhost",
      "Port": 1025,
      "Username": "noreply@acme.example",
      "Password": "",
      "APIKey": "",
      "APIToken": "",
      "Endpoint": "",
      "HTTPMethod": "POST",
      "Headers": {},
      "QueryParams": {},
      "HTTPPayload": null,
      "PayloadFormat": "",
      "HTTPContentType": "",
      "HTTPAuth": "",
      "HTTPAuthHeader": "",
      "HTTPAuthQuery": "",
      "HTTPAuthPrefix": "Bearer",
      "MaxConnsPerHost": 0,
      "MaxIdleConns": 0,
      "MaxIdleConnsHost": 0,
      "DisableKeepAlives": false,
      "SMTPAuth": "",
      "HTMLTemplatePath": "templates/pipeline_welcome_mailhog.html",
      "TextTemplatePath": "templates/pipeline_welcome_mailhog.txt",
      "BodyTemplatePath": "",
      "AdditionalData": {
        "login_url": "https://app.example/login",
        "tour_url": "https://app.example/tour",
        "workflow_steps": [
          {
            "delay_seconds": 0,
            "name": "welcome",
            "provider_priority": [
              "smtp"
            ],
            "retry_count": 2,
            "retry_delay_seconds": 5,
            "subject": "Welcome to Acme — Start here"
          },
          {
            "body": "Hi demo@example.org, just checking in to see how things are going. Login: https://app.example/login",
            "delay_seconds": 60,
            "name": "followup",
            "provider_priority": [
              "smtp"
            ],
            "retry_count": 2,
            "subject": "A quick follow-up"
          }
        ]
      },
      "AWSRegion": "",
      "AWSAccessKey": "",
      "AWSSecretKey": "",
      "AWSSessionToken": "",
      "UseTLS": false,
      "UseSSL": false,
      "SkipTLSVerify": false,
      "Timeout": 15000000000,
      "RetryCount": 2,
      "RetryDelay": 5000000000,
      "MaxRetryDelay": 0,
      "ProviderPriority": [
        "smtp"
      ]
    },
    "run_at": "2025-12-20T16:36:09.872917332Z",
    "attempts": 0,
    "meta": {
      "name": "followup",
      "step": "followup",
      "step_index": 1
    }
  }
]